cmd/__init__.py
cmd/cpc-fusion
cpc_fusion/__init__.py
cpc_fusion/admin.py
cpc_fusion/contract.py
cpc_fusion/cpc.py
cpc_fusion/datastructures.py
cpc_fusion/default_contracts.py
cpc_fusion/eth.py
cpc_fusion/exceptions.py
cpc_fusion/iban.py
cpc_fusion/main.py
cpc_fusion/manager.py
cpc_fusion/miner.py
cpc_fusion/module.py
cpc_fusion/net.py
cpc_fusion/parity.py
cpc_fusion/personal.py
cpc_fusion/pm.py
cpc_fusion/shh.py
cpc_fusion/testing.py
cpc_fusion/txpool.py
cpc_fusion/version.py
cpc_fusion/_utils/__init__.py
cpc_fusion/_utils/abi.py
cpc_fusion/_utils/blocks.py
cpc_fusion/_utils/caching.py
cpc_fusion/_utils/contracts.py
cpc_fusion/_utils/datatypes.py
cpc_fusion/_utils/decorators.py
cpc_fusion/_utils/empty.py
cpc_fusion/_utils/encoding.py
cpc_fusion/_utils/ens.py
cpc_fusion/_utils/events.py
cpc_fusion/_utils/filters.py
cpc_fusion/_utils/formatters.py
cpc_fusion/_utils/function_identifiers.py
cpc_fusion/_utils/http.py
cpc_fusion/_utils/hypothesis.py
cpc_fusion/_utils/math.py
cpc_fusion/_utils/normalizers.py
cpc_fusion/_utils/request.py
cpc_fusion/_utils/rpc_abi.py
cpc_fusion/_utils/threads.py
cpc_fusion/_utils/transactions.py
cpc_fusion/_utils/validation.py
cpc_fusion/_utils/windows.py
cpc_fusion/_utils/module_testing/__init__.py
cpc_fusion/_utils/module_testing/emitter_contract.py
cpc_fusion/_utils/module_testing/eth_module.py
cpc_fusion/_utils/module_testing/math_contract.py
cpc_fusion/_utils/module_testing/net_module.py
cpc_fusion/_utils/module_testing/parity_module.py
cpc_fusion/_utils/module_testing/personal_module.py
cpc_fusion/_utils/module_testing/version_module.py
cpc_fusion/_utils/module_testing/web3_module.py
cpc_fusion/_utils/toolz/__init__.py
cpc_fusion/_utils/toolz/curried.py
cpc_fusion/auto/__init__.py
cpc_fusion/auto/gethdev.py
cpc_fusion/auto/http.py
cpc_fusion/auto/infura.py
cpc_fusion/auto/ipc.py
cpc_fusion/auto/websocket.py
cpc_fusion/cmd/__init__.py
cpc_fusion/cmd/account.py
cpc_fusion/cmd/version.py
cpc_fusion/cmd/view_func.py
cpc_fusion-0.1.29.dist-info/LICENSE
cpc_fusion-0.1.29.dist-info/METADATA
cpc_fusion-0.1.29.dist-info/WHEEL
cpc_fusion-0.1.29.dist-info/top_level.txt
cpc_fusion-0.1.29.dist-info/RECORD
